etherscan/__init__.py
etherscan/errors.py
etherscan/etherscan.py
etherscan-0.3.0.dist-info/LICENSE
etherscan-0.3.0.dist-info/METADATA
etherscan-0.3.0.dist-info/WHEEL
etherscan-0.3.0.dist-info/top_level.txt
etherscan-0.3.0.dist-info/RECORD
