Metadata-Version: 2.1
Name: etherscan
Version: 0.3.0
Summary: Etherscan.io API wrapper
Home-page: https://github.com/neoctobers/etherscan
Author: @neoctobers
Author-email: neoctobers@gmail.com
License: UNKNOWN
Platform: UNKNOWN
Classifier: Programming Language :: Python :: 3
Classifier: License :: OSI Approved :: MIT License
Classifier: Operating System :: OS Independent
